jpviz/__init__.py
jpviz/dot/__init__.py
jpviz/dot/graph.py
jpviz/dot/graph_utils.py
jpviz/dot/styling.py
jpviz/dot/utils.py
jpviz-0.1.7.dist-info/LICENSE
jpviz-0.1.7.dist-info/METADATA
jpviz-0.1.7.dist-info/WHEEL
jpviz-0.1.7.dist-info/RECORD
