Metadata-Version: 2.1
Name: jpviz
Version: 0.1.7
Summary: Jaxpr Visualisation Tool
Home-page: https://github.com/zombie-einstein/jaxpr-viz
License: MIT
Keywords: JAX,Computation Graph
Author: Zombie-Einstein
Author-email: zombie-einstein@proton.me
Requires-Python: >=3.10,<3.13
Classifier: Development Status :: 4 - Beta
Classifier: License :: OSI Approved :: MIT License
Classifier: Programming Language :: Python
Classifier: Programming Language :: Python :: 3
Classifier: Programming Language :: Python :: 3.10
Classifier: Programming Language :: Python :: 3.11
Classifier: Programming Language :: Python :: 3.12
Classifier: Programming Language :: Python :: Implementation :: CPython
Classifier: Programming Language :: Python :: Implementation :: PyPy
Requires-Dist: jax (>=0.4.14,<0.5.0)
Requires-Dist: pydot (>=1.4.2,<2.0.0)
Requires-Dist: scipy (>=1.10.0,<2.0.0)
Project-URL: Repository, https://github.com/zombie-einstein/jaxpr-viz
